<annotation>
	<folder>allimages</folder>
	<filename>0 (1548).jpg</filename>
	<path>C:\Users\Lenovo\Desktop\datadetseg\det\allimages\0 (1548).jpg</path>
	<source>
		<database>Unknown</database>
	</source>
	<size>
		<width>709</width>
		<height>500</height>
		<depth>3</depth>
	</size>
	<segmented>0</segmented>
	<object>
		<name>person</name>
		<pose>Unspecified</pose>
		<truncated>0</truncated>
		<difficult>0</difficult>
		<bndbox>
			<xmin>165</xmin>
			<ymin>147</ymin>
			<xmax>312</xmax>
			<ymax>380</ymax>
		</bndbox>
	</object>
	<object>
		<name>person</name>
		<pose>Unspecified</pose>
		<truncated>0</truncated>
		<difficult>0</difficult>
		<bndbox>
			<xmin>351</xmin>
			<ymin>89</ymin>
			<xmax>427</xmax>
			<ymax>186</ymax>
		</bndbox>
	</object>
	<object>
		<name>person</name>
		<pose>Unspecified</pose>
		<truncated>0</truncated>
		<difficult>0</difficult>
		<bndbox>
			<xmin>60</xmin>
			<ymin>125</ymin>
			<xmax>145</xmax>
			<ymax>213</ymax>
		</bndbox>
	</object>
	<object>
		<name>person</name>
		<pose>Unspecified</pose>
		<truncated>1</truncated>
		<difficult>0</difficult>
		<bndbox>
			<xmin>1</xmin>
			<ymin>154</ymin>
			<xmax>96</xmax>
			<ymax>396</ymax>
		</bndbox>
	</object>
	<object>
		<name>person</name>
		<pose>Unspecified</pose>
		<truncated>0</truncated>
		<difficult>0</difficult>
		<bndbox>
			<xmin>468</xmin>
			<ymin>95</ymin>
			<xmax>553</xmax>
			<ymax>267</ymax>
		</bndbox>
	</object>
	<object>
		<name>person</name>
		<pose>Unspecified</pose>
		<truncated>0</truncated>
		<difficult>0</difficult>
		<bndbox>
			<xmin>633</xmin>
			<ymin>78</ymin>
			<xmax>707</xmax>
			<ymax>170</ymax>
		</bndbox>
	</object>
</annotation>
