<annotation>
	<folder>allimages</folder>
	<filename>0 (399).jpg</filename>
	<path>C:\Users\Lenovo\Desktop\datadetseg\det\allimages\0 (399).jpg</path>
	<source>
		<database>Unknown</database>
	</source>
	<size>
		<width>2160</width>
		<height>1995</height>
		<depth>3</depth>
	</size>
	<segmented>0</segmented>
	<object>
		<name>clothes</name>
		<pose>Unspecified</pose>
		<truncated>0</truncated>
		<difficult>0</difficult>
		<bndbox>
			<xmin>113</xmin>
			<ymin>210</ymin>
			<xmax>2013</xmax>
			<ymax>1725</ymax>
		</bndbox>
	</object>
</annotation>
