<annotation>
	<folder>allimages</folder>
	<filename>0 (402).jpg</filename>
	<path>C:\Users\Lenovo\Desktop\datadetseg\det\allimages\0 (402).jpg</path>
	<source>
		<database>Unknown</database>
	</source>
	<size>
		<width>956</width>
		<height>1276</height>
		<depth>3</depth>
	</size>
	<segmented>0</segmented>
	<object>
		<name>clothes</name>
		<pose>Unspecified</pose>
		<truncated>0</truncated>
		<difficult>0</difficult>
		<bndbox>
			<xmin>44</xmin>
			<ymin>373</ymin>
			<xmax>893</xmax>
			<ymax>1094</ymax>
		</bndbox>
	</object>
</annotation>
