<annotation>
	<folder>allimages</folder>
	<filename>0 (557).jpg</filename>
	<path>C:\Users\Lenovo\Desktop\datadetseg\det\allimages\0 (557).jpg</path>
	<source>
		<database>Unknown</database>
	</source>
	<size>
		<width>600</width>
		<height>400</height>
		<depth>3</depth>
	</size>
	<segmented>0</segmented>
	<object>
		<name>clothes</name>
		<pose>Unspecified</pose>
		<truncated>1</truncated>
		<difficult>0</difficult>
		<bndbox>
			<xmin>24</xmin>
			<ymin>12</ymin>
			<xmax>595</xmax>
			<ymax>400</ymax>
		</bndbox>
	</object>
</annotation>
