<annotation>
	<folder>allimages</folder>
	<filename>0 (951).jpg</filename>
	<path>C:\Users\Lenovo\Desktop\datadetseg\det\allimages\0 (951).jpg</path>
	<source>
		<database>Unknown</database>
	</source>
	<size>
		<width>3016</width>
		<height>3450</height>
		<depth>3</depth>
	</size>
	<segmented>0</segmented>
	<object>
		<name>clothes</name>
		<pose>Unspecified</pose>
		<truncated>1</truncated>
		<difficult>0</difficult>
		<bndbox>
			<xmin>10</xmin>
			<ymin>402</ymin>
			<xmax>3016</xmax>
			<ymax>3406</ymax>
		</bndbox>
	</object>
</annotation>
